tailwind_colors-1.4.1.dist-info/METADATA
tailwind_colors-1.4.1.dist-info/WHEEL
tailwind_colors-1.4.1.dist-info/entry_points.txt
tailwind_colors-1.4.1.dist-info/licenses/LICENSE.md
tailwind_colors/__init__.py
tailwind_colors/py.typed
tailwind_colors-1.4.1.dist-info/RECORD
